[
  {
    "level": "error",
    "message": "Database connection failed.",
    "resourceId": "server-1234",
    "timestamp": "2023-09-15T08:00:00Z",
    "traceId": "abc-xyz-123",
    "spanId": "span-456",
    "commit": "5e5342f",
    "metadata": {
      "parentResourceId": "server-5678"
    }
  },
  {
    "level": "warn",
    "message": "High memory usage detected.",
    "resourceId": "server-4321",
    "timestamp": "2023-09-15T09:30:00Z",
    "traceId": "def-uvw-456",
    "spanId": "span-789",
    "commit": "6f6432a",
    "metadata": {
      "parentResourceId": "server-8765"
    }
  },
  {
    "level": "info",
    "message": "User login successful.",
    "resourceId": "auth-001",
    "timestamp": "2023-09-15T10:00:00Z",
    "traceId": "ghi-rst-789",
    "spanId": "span-012",
    "commit": "7g7543b",
    "metadata": {
      "parentResourceId": "auth-002"
    }
  },
  {
    "level": "debug",
    "message": "Cache refreshed.",
    "resourceId": "cache-101",
    "timestamp": "2023-09-15T10:15:00Z",
    "traceId": "jkl-opq-012",
    "spanId": "span-345",
    "commit": "8h8654c",
    "metadata": {
      "parentResourceId": "cache-202"
    }
  },
  {
    "level": "error",
    "message": "Payment gateway timeout.",
    "resourceId": "payment-345",
    "timestamp": "2023-09-15T11:00:00Z",
    "traceId": "mno-lmn-345",
    "spanId": "span-678",
    "commit": "9i9765d",
    "metadata": {
      "parentResourceId": "payment-678"
    }
  },
  {
    "level": "warn",
    "message": "Disk space running low.",
    "resourceId": "storage-789",
    "timestamp": "2023-09-15T11:30:00Z",
    "traceId": "pqr-stu-678",
    "spanId": "span-901",
    "commit": "0j0876e",
    "metadata": {
      "parentResourceId": "storage-890"
    }
  },
  {
    "level": "info",
    "message": "Scheduled job completed.",
    "resourceId": "scheduler-012",
    "timestamp": "2023-09-15T12:00:00Z",
    "traceId": "vwx-yza-901",
    "spanId": "span-234",
    "commit": "1k1987f",
    "metadata": {
      "parentResourceId": "scheduler-123"
    }
  },
  {
    "level": "debug",
    "message": "User session refreshed.",
    "resourceId": "auth-003",
    "timestamp": "2023-09-15T12:30:00Z",
    "traceId": "bcd-efg-234",
    "spanId": "span-567",
    "commit": "2l2098g",
    "metadata": {
      "parentResourceId": "auth-004"
    }
  },
  {
    "level": "error",
    "message": "Unhandled exception in API endpoint.",
    "resourceId": "api-555",
    "timestamp": "2023-09-15T13:00:00Z",
    "traceId": "hij-klm-567",
    "spanId": "span-890",
    "commit": "3m3109h",
    "metadata": {
      "parentResourceId": "api-666"
    }
  },
  {
    "level": "warn",
    "message": "API rate limit approaching.",
    "resourceId": "api-777",
    "timestamp": "2023-09-15T13:30:00Z",
    "traceId": "nop-qrs-890",
    "spanId": "span-123",
    "commit": "4n4210i",
    "metadata": {
      "parentResourceId": "api-888"
    }
  },
  {
    "level": "info",
    "message": "New user registration.",
    "resourceId": "user-999",
    "timestamp": "2023-09-15T14:00:00Z",
    "traceId": "tuv-wxy-123",
    "spanId": "span-456",
    "commit": "5o5311j",
    "metadata": {
      "parentResourceId": "user-000"
    }
  },
  {
    "level": "debug",
    "message": "Configuration file reloaded.",
    "resourceId": "config-321",
    "timestamp": "2023-09-15T14:30:00Z",
    "traceId": "zab-cde-456",
    "spanId": "span-789",
    "commit": "6p6412k",
    "metadata": {
      "parentResourceId": "config-654"
    }
  },
  {
    "level": "debug",
    "message": "Configuration file lost.",
    "resourceId": "config-341",
    "timestamp": "2023-09-15T14:30:00Z",
    "traceId": "zaer-cde-456",
    "spanId": "span-719",
    "commit": "6p6434k",
    "metadata": {
      "parentResourceId": "config-600"
    }
  }
]
